{
    "methods": [
        {
            "type": "Method",
            "parameter": [
                {
                    "name": "callback"
                }
            ],
            "annotations": {},
            "definedInFile": "sprd/manager/IBasketManager.js",
            "lineNumbers": [
                23,
                25
            ],
            "name": "_initBasket",
            "visibility": "protected"
        },
        {
            "type": "Method",
            "parameter": [
                {
                    "name": "element"
                },
                {
                    "name": "quantity"
                },
                {
                    "name": "callback"
                }
            ],
            "annotations": {},
            "definedInFile": "sprd/manager/IBasketManager.js",
            "lineNumbers": [
                27,
                29
            ],
            "name": "addElementToBasket",
            "visibility": "public"
        },
        {
            "type": "Method",
            "parameter": [
                {
                    "name": "callback"
                }
            ],
            "annotations": {},
            "definedInFile": "sprd/manager/IBasketManager.js",
            "lineNumbers": [
                5,
                21
            ],
            "name": "initBasket",
            "visibility": "public"
        }
    ],
    "staticMethods": [],
    "defaults": {},
    "properties": {},
    "fqClassName": "sprd.manager.IBasketManager",
    "inherit": "js.core.Component",
    "dependencies": [
        "js.core.Component"
    ],
    "type": "js",
    "file": "sprd/manager/IBasketManager.js",
    "package": "sprd.manager",
    "inheritancePath": [
        "js.core.Component"
    ]
}